horizon_data_core/__init__.py
horizon_data_core/api.py
horizon_data_core/base_types.py
horizon_data_core/client.py
horizon_data_core/helpers.py
horizon_data_core/iceberg_repository.py
horizon_data_core/kafka_config.py
horizon_data_core/kafka_producer.py
horizon_data_core/logging.py
horizon_data_core/orm_types.py
horizon_data_core/py.typed
horizon_data_core/schema_discovery.py
horizon_data_core/sdk.py
horizon_data_core/resources/__init__.py
horizon_data_core/resources/database.py
horizon_data_core/resources/postgres_dataframe_io_manager.py
horizon_data_core/resources/py.typed
horizon_data_core/resources/s3.py
horizon_data_core-4.0.1.dist-info/METADATA
horizon_data_core-4.0.1.dist-info/WHEEL
horizon_data_core-4.0.1.dist-info/RECORD
