Metadata-Version: 2.4
Name: horizon-data-core
Version: 4.0.1
Summary: Horizon’s core data SDK
Author-email: Spear AI <org@spear.ai>
Keywords: Horizon,SDK,Spear AI
Classifier: Programming Language :: Python :: 3 :: Only
Classifier: Programming Language :: Python :: 3.12
Requires-Python: <3.13,>=3.12
Requires-Dist: confluent-kafka>=2.12.2
Requires-Dist: dagster-aws>=0.22.1
Requires-Dist: dagster-iceberg>=0.3.3
Requires-Dist: dagster-pandera>=0.22.1
Requires-Dist: dagster>=1.6.1
Requires-Dist: geojson>=3
Requires-Dist: pandas>=2
Requires-Dist: pandera[mypy]>=0.18
Requires-Dist: polars>=1.33.1
Requires-Dist: psycopg2-binary>=2.9.10
Requires-Dist: pyarrow>=21.0.0
Requires-Dist: pydantic-settings>=2.12.0
Requires-Dist: pydantic>=2.5
Requires-Dist: pyiceberg[pyarrow,s3fs]>=0.10
Requires-Dist: s3path>=0.6
Requires-Dist: sqlalchemy[mypy]>=2.0.36
Requires-Dist: structlog>=25.4.0
Requires-Dist: turfpy>=0.0.7
Provides-Extra: testing
Requires-Dist: pytest>=8.3; extra == 'testing'
